setup.py
easywsgi/__init__.py
easywsgi.egg-info/PKG-INFO
easywsgi.egg-info/SOURCES.txt
easywsgi.egg-info/dependency_links.txt
easywsgi.egg-info/not-zip-safe
easywsgi.egg-info/top_level.txt